pydify_sdk/__init__.py
pydify_sdk/base.py
pydify_sdk/chatflow.py
pydify_sdk/config.py
pydify_sdk/schema.py
pydify_sdk/utils.py
pydify_sdk/wokeflow.py
pydify_sdk/constants/__init__.py
pydify_sdk/constants/base.py
pydify_sdk/constants/const_basic.py
pydify_sdk/constants/input.py
pydify_sdk-0.1.1.dist-info/METADATA
pydify_sdk-0.1.1.dist-info/WHEEL
pydify_sdk-0.1.1.dist-info/licenses/LICENSE
pydify_sdk-0.1.1.dist-info/RECORD
