Metadata-Version: 2.4
Name: pydify_sdk
Version: 0.1.1
Summary: A package for quickly calling dify
Project-URL: Homepage, https://github.com/Dorain-An/dify-sdk
Project-URL: Issues, https://github.com/Dorain-An/dify-sdk/issues
Author-email: jinlingfeng <jinlingfeng2020@163.com>
License:                                  Apache License
License-File: LICENSE
Classifier: Operating System :: OS Independent
Classifier: Programming Language :: Python :: 3
Requires-Python: >=3.11
Requires-Dist: pydantic
Requires-Dist: pydantic-settings
Requires-Dist: requests
Requires-Dist: sseclient-py
